Metadata-Version: 2.1
Name: xinabox-CHIP
Version: 0.0.1
Summary: a template package for xchips
Home-page: https://github.com/xinabox/Python-XCHIP
Author: Luqmaan Baboo
Author-email: luqmaanbaboo@gmail.com
License: UNKNOWN
Platform: UNKNOWN
Classifier: Programming Language :: Python :: 3
Classifier: License :: OSI Approved :: MIT License
Classifier: Operating System :: OS Independent
Requires-Python: >=3.6
